binary_trie/__init__.py
binary_trie/encoding.py
binary_trie/helpers.py
binary_trie/trie.py
binary_trie-1.0.3.dist-info/LICENSE
binary_trie-1.0.3.dist-info/METADATA
binary_trie-1.0.3.dist-info/WHEEL
binary_trie-1.0.3.dist-info/top_level.txt
binary_trie-1.0.3.dist-info/RECORD
